[{ "id": "Bienvenidos", "parent" : "#", "text": "Bienvenidos", "a_attr": {"href": "Bienvenidos.html"}  },{ "id": "Observaciones", "parent" : "Bienvenidos", "text": "Observaciones", "a_attr": {"href": "Observaciones.html"}  },{ "id": "LasVentanas", "parent" : "#", "text": "Las Ventanas", "a_attr": {"href": "LasVentanas.html"}  },{ "id": "Perfil", "parent" : "LasVentanas", "text": "Perfil", "a_attr": {"href": "Perfil.html"}  },{ "id": "CrearPeticion", "parent" : "LasVentanas", "text": "Crear Petición", "a_attr": {"href": "CrearPeticion.html"}  },{ "id": "Verpeticiones", "parent" : "LasVentanas", "text": "Ver peticiones", "a_attr": {"href": "Verpeticiones.html"}  },{ "id": "Elmenu", "parent" : "LasVentanas", "text": "El menú", "a_attr": {"href": "Elmenu.html"}  }]